DAVE/nlp/Clark.py
DAVE/nlp/Clarke.py
DAVE/nlp/HAL.py
DAVE/nlp/Stanley.py
DAVE/nlp/__init__.py
DAVE/scraper/DiscoveryOne.py
DAVE/scraper/Sentinel.py
DAVE/scraper/__init__.py
davebot-1.0.1.dist-info/LICENSE
davebot-1.0.1.dist-info/METADATA
davebot-1.0.1.dist-info/WHEEL
davebot-1.0.1.dist-info/top_level.txt
davebot-1.0.1.dist-info/RECORD
