Metadata-Version: 2.1
Name: davebot
Version: 1.0.1
Summary: A screenplay bot
Home-page: https://github.com/DED8IRD/D.A.V.E
Author: Eunika Wu
Author-email: eunika@pdxcodeguild.com
License: UNKNOWN
Platform: UNKNOWN
Classifier: Programming Language :: Python :: 3
Classifier: License :: OSI Approved :: MIT License
Classifier: Operating System :: OS Independent
Requires-Dist: beautifulsoup4 (==4.8.0)
Requires-Dist: fpdf (==1.7.2)
Requires-Dist: markovify (==0.7.2)
Requires-Dist: requests (==2.22.0)
